CHANGELOG.md
flake8_name_migrations/__init__.py
flake8_name_migrations/plugin.py
flake8_name_migrations/py.typed
flake8_name_migrations-0.1.0.dist-info/entry_points.txt
flake8_name_migrations-0.1.0.dist-info/WHEEL
flake8_name_migrations-0.1.0.dist-info/METADATA
flake8_name_migrations-0.1.0.dist-info/RECORD
